{
  "name": "Iron Wallet: Ripple (Testnet)",
  "logoUri": "",
  "timestamp": "2025-07-28T15:36:28Z",
  "status": "active",
  "assets": [
    {
      "asset_id": "cldejolim000008je2ffj9fr0",
      "externalId": "ripple",
      "name": "Ripple Test",
      "symbol": "XRP",
      "decimals": 6,
      "logoUri": "dev_assets/cldejolim000008je2ffj9fr0/logo.png",
      "status": "active",
      "default": true,
      "displayDecimals": 4
    },
    {
      "asset_id": "cldlhp47a000008mm4i2x6da5",
      "externalId": "usd-coin",
      "type": "Ripple",
      "address": "rLL22g9ANawaiU4P4PoWvAtBUEhRsuR61i",
      "name": "USDT Test",
      "symbol": "USDT",
      "decimals": 6,
      "logoUri": "dev_assets/cldlhp47a000008mm4i2x6da5/logo.png",
      "status": "active",
      "default": true,
      "displayDecimals": 4,
      "explorer": ""
    }
  ],
  "version": {
    "major": 0,
    "minor": 0,
    "patch": 8
  }
}