{
  "assets": [
    {
      "address": null,
      "asset_id": "cmkxv8smw0000gkfms23z7jpp",
      "chainId": 8453,
      "decimals": 18,
      "default": true,
      "displayDecimals": 4,
      "explorer": null,
      "externalId": "base",
      "logoUri": "assets/cmkxv8smw0000gkfms23z7jpp/logo.png",
      "name": "Base",
      "status": "active",
      "symbol": "ETH",
      "type": null
    },
    {
      "address": "0x833589fcd6edb6e08f4c7c32d4f71b54bda02913",
      "asset_id": "cmkxujgim0000ukfmjb1rs91q",
      "chainId": 8453,
      "decimals": 6,
      "default": false,
      "displayDecimals": 4,
      "explorer": "https://basescan.org/token/0x833589fcd6edb6e08f4c7c32d4f71b54bda02913",
      "externalId": "usd-coin",
      "logoUri": "assets/cmkxujgim0000ukfmjb1rs91q/logo.png",
      "name": "USD Coin",
      "status": "active",
      "symbol": "USDC",
      "type": "ERC20"
    },
    {
      "address": "0x311935cd80b76769bf2ecc9d8ab7635b2139cf82",
      "asset_id": "cmkxvpvjb0000fcfmwptnct1d",
      "chainId": 8453,
      "decimals": 9,
      "default": false,
      "displayDecimals": 4,
      "explorer": "https://basescan.org/token/0x311935cd80b76769bf2ecc9d8ab7635b2139cf82",
      "externalId": "base-bridged-sol-base",
      "logoUri": "/assets/cmkxvpvjb0000fcfmwptnct1d/logo.png",
      "name": "Base Bridged SOL (Base)",
      "status": "active",
      "symbol": "sol",
      "type": "ERC20"
    },
    {
      "address": "0xcbb7c0000ab88b473b1f5afd9ef808440eed33bf",
      "asset_id": "cmkxvwdv0000058fmu19q9cg3",
      "chainId": 8453,
      "decimals": 8,
      "default": false,
      "displayDecimals": 4,
      "explorer": "https://basescan.org/token/0xcbb7c0000ab88b473b1f5afd9ef808440eed33bf",
      "externalId": "coinbase-wrapped-btc",
      "logoUri": "/assets/cmkxvwdv0000058fmu19q9cg3/logo.png",
      "name": "Coinbase Wrapped BTC",
      "status": "active",
      "symbol": "cbbtc",
      "type": "ERC20"
    },
    {
      "address": "0x5d3a1ff2b6bab83b63cd9ad0787074081a52ef34",
      "asset_id": "cmkxvwvnf00000ofm7yo752kt",
      "chainId": 8453,
      "decimals": 18,
      "default": false,
      "displayDecimals": 4,
      "explorer": "https://basescan.org/token/0x5d3a1ff2b6bab83b63cd9ad0787074081a52ef34",
      "externalId": "ethena-usde",
      "logoUri": "/assets/cmkxvwvnf00000ofm7yo752kt/logo.png",
      "name": "Ethena USDe",
      "status": "active",
      "symbol": "usde",
      "type": "ERC20"
    },
    {
      "address": "0x50c5725949a6f0c72e6c4a641f24049a917db0cb",
      "asset_id": "cmkxvxiui0000kkfmkrreoxi5",
      "chainId": 8453,
      "decimals": 18,
      "default": false,
      "displayDecimals": 4,
      "explorer": "https://basescan.org/token/0x50c5725949a6f0c72e6c4a641f24049a917db0cb",
      "externalId": "l2-standard-bridged-dai-base",
      "logoUri": "/assets/cmkxvxiui0000kkfmkrreoxi5/logo.png",
      "name": "L2 Standard Bridged DAI (Base)",
      "status": "active",
      "symbol": "dai",
      "type": "ERC20"
    },
    {
      "address": "0x60a3e35cc302bfa44cb288bc5a4f316fdb1adb42",
      "asset_id": "cmkxvym540000pwfmbo20eyce",
      "chainId": 8453,
      "decimals": 6,
      "default": false,
      "displayDecimals": 4,
      "explorer": "https://basescan.org/token/0x60a3e35cc302bfa44cb288bc5a4f316fdb1adb42",
      "externalId": "euro-coin",
      "logoUri": "/assets/cmkxvym540000pwfmbo20eyce/logo.png",
      "name": "EURC",
      "status": "active",
      "symbol": "eurc",
      "type": "ERC20"
    },
    {
      "address": "0x820c137fa70c8691f0e44dc420a5e53c168921dc",
      "asset_id": "cmkxvzfuk000000fmqoliqqcn",
      "chainId": 8453,
      "decimals": 18,
      "default": false,
      "displayDecimals": 4,
      "explorer": "https://basescan.org/token/0x820c137fa70c8691f0e44dc420a5e53c168921dc",
      "externalId": "usds",
      "logoUri": "/assets/cmkxvzfuk000000fmqoliqqcn/logo.png",
      "name": "USDS",
      "status": "active",
      "symbol": "usds",
      "type": "ERC20"
    },
    {
      "address": "0x0b3e328455c4059eeb9e3f84b5543f74e24e7e1b",
      "asset_id": "cmkxw10nx0000e0fmgkggml7c",
      "chainId": 8453,
      "decimals": 18,
      "default": false,
      "displayDecimals": 4,
      "explorer": "https://basescan.org/token/0x0b3e328455c4059eeb9e3f84b5543f74e24e7e1b",
      "externalId": "virtual-protocol",
      "logoUri": "/assets/cmkxw10nx0000e0fmgkggml7c/logo.png",
      "name": "Virtuals Protocol",
      "status": "active",
      "symbol": "virtual",
      "type": "ERC20"
    },
    {
      "address": "0xb6fe221fe9eef5aba221c348ba20a1bf5e73624c",
      "asset_id": "cmkxw2ah700003wfm822urewm",
      "chainId": 8453,
      "decimals": 18,
      "default": false,
      "displayDecimals": 4,
      "explorer": "https://basescan.org/token/0xb6fe221fe9eef5aba221c348ba20a1bf5e73624c",
      "externalId": "rocket-pool-eth",
      "logoUri": "/assets/cmkxw2ah700003wfm822urewm/logo.png",
      "name": "Rocket Pool ETH",
      "status": "active",
      "symbol": "reth",
      "type": "ERC20"
    },
    {
      "address": "0x58538e6a46e07434d7e7375bc268d3cb839c0133",
      "asset_id": "cmkxw2qwd0000d0fmvfhgfacl",
      "chainId": 8453,
      "decimals": 18,
      "default": false,
      "displayDecimals": 4,
      "explorer": "https://basescan.org/token/0x58538e6a46e07434d7e7375bc268d3cb839c0133",
      "externalId": "ethena",
      "logoUri": "/assets/cmkxw2qwd0000d0fmvfhgfacl/logo.png",
      "name": "Ethena",
      "status": "active",
      "symbol": "ena",
      "type": "ERC20"
    },
    {
      "address": "0x63706e401c06ac8513145b7687a14804d17f814b",
      "asset_id": "cmkxw49gn0000zsfmwobforuo",
      "chainId": 8453,
      "decimals": 18,
      "default": false,
      "displayDecimals": 4,
      "explorer": "https://basescan.org/token/0x63706e401c06ac8513145b7687a14804d17f814b",
      "externalId": "aave",
      "logoUri": "/assets/cmkxw49gn0000zsfmwobforuo/logo.png",
      "name": "Aave",
      "status": "active",
      "symbol": "aave",
      "type": "ERC20"
    }
  ],
  "logoUri": "",
  "name": "Iron Wallet: Base",
  "statu": null,
  "timestamp": "2024-10-25T23:11:09.042Z",
  "version": {
    "major": 0,
    "minor": 0,
    "patch": 1
  }
}
